MANIFEST.in
README.md
README.mrab-regex.rst
setup.cfg
setup.py
cpytraceafl_regex.egg-info/PKG-INFO
cpytraceafl_regex.egg-info/SOURCES.txt
cpytraceafl_regex.egg-info/dependency_links.txt
cpytraceafl_regex.egg-info/requires.txt
cpytraceafl_regex.egg-info/top_level.txt
docs/Features.html
docs/Features.rst
docs/UnicodeProperties.rst
regex_2/__init__.py
regex_2/_regex.c
regex_2/_regex.h
regex_2/_regex_core.py
regex_2/_regex_unicode.c
regex_2/_regex_unicode.h
regex_2/regex.py
regex_2/test_regex.py
regex_3/__init__.py
regex_3/_regex.c
regex_3/_regex.h
regex_3/_regex_core.py
regex_3/_regex_unicode.c
regex_3/_regex_unicode.h
regex_3/cpytraceafl.h
regex_3/regex.py
regex_3/test_regex.py
tests_cpytraceafl/test_match.py
tools/build_regex_unicode.py