Metadata-Version: 2.1
Name: cpytraceafl-regex
Version: 0.2.0
Summary: A modified version of mrab-regex with added cpytraceafl instrumentation
Home-page: https://github.com/risicle/cpytraceafl-regex
Author: Robert Scott
Author-email: code@humanleg.org.uk
License: Python Software Foundation License
Platform: UNKNOWN
Classifier: Development Status :: 5 - Production/Stable
Classifier: Intended Audience :: Developers
Classifier: License :: OSI Approved :: Python Software Foundation License
Classifier: Operating System :: OS Independent
Classifier: Programming Language :: Python :: 2.7
Classifier: Programming Language :: Python :: 3.5
Classifier: Programming Language :: Python :: 3.6
Classifier: Programming Language :: Python :: 3.7
Classifier: Programming Language :: Python :: 3.8
Classifier: Topic :: Scientific/Engineering :: Information Analysis
Classifier: Topic :: Software Development :: Libraries :: Python Modules
Classifier: Topic :: Text Processing
Classifier: Topic :: Text Processing :: General
